pylabview_helpers/__init__.py
pylabview_helpers/vi.py
pylabview_helpers-0.1.2.dist-info/LICENSE
pylabview_helpers-0.1.2.dist-info/WHEEL
pylabview_helpers-0.1.2.dist-info/METADATA
pylabview_helpers-0.1.2.dist-info/RECORD
